xrcg/__init__.py
xrcg/__main__.py
xrcg/_version.py
xrcg/cli.py
xrcg/commands.json
xrcg/commands/__init__.py
xrcg/commands/catalog.py
xrcg/commands/config.py
xrcg/commands/generate_code.py
xrcg/commands/list_templates.py
xrcg/commands/manifest.py
xrcg/commands/validate_definitions.py
xrcg/common/config.py
xrcg/common/model.py
xrcg/dependencies/.gitignore
xrcg/dependencies/cs/net80/dependencies.csproj
xrcg/dependencies/cs/net90/dependencies.csproj
xrcg/dependencies/go/go121/go.mod
xrcg/dependencies/java/jdk21/pom.xml
xrcg/dependencies/python/py312/requirements.txt
xrcg/dependencies/typescript/node22/package.json
xrcg/generator/__init__.py
xrcg/generator/context_stacks_manager.py
xrcg/generator/generator_context.py
xrcg/generator/jinja_extensions.py
xrcg/generator/jinja_filters.py
xrcg/generator/resource_processor.py
xrcg/generator/schema_processor.py
xrcg/generator/schema_type_extractor.py
xrcg/generator/schema_utils.py
xrcg/generator/template_renderer.py
xrcg/generator/url_utils.py
xrcg/generator/xregistry_loader.py
xrcg/schemas/_model.json
xrcg/schemas/document-schema.json
xrcg/schemas/endpoint.json
xrcg/schemas/message.json
xrcg/schemas/model.json
xrcg/schemas/schema.json
xrcg/templates/asaql/_templateinfo.json
xrcg/templates/asaql/_schemas/_json.asaql.jinja
xrcg/templates/asaql/dispatch/JobConfig.json.jinja
xrcg/templates/asaql/dispatch/_templateinfo.json
xrcg/templates/asaql/dispatch/{projectname}.asaql.jinja
xrcg/templates/asaql/dispatch/{projectname}.json.jinja
xrcg/templates/asaql/dispatch/SampleEvents/sampleevents.jinja
xrcg/templates/asaql/dispatchpayload/JobConfig.json.jinja
xrcg/templates/asaql/dispatchpayload/_templateinfo.json
xrcg/templates/asaql/dispatchpayload/_{projectname}.asaql.jinja
xrcg/templates/asaql/dispatchpayload/{projectname}.json.jinja
xrcg/templates/asaql/dispatchpayload/SampleEvents/sampleevents.jinja
xrcg/templates/asyncapi/_templateinfo.json
xrcg/templates/asyncapi/consumer/_templateinfo.json
xrcg-0.9.9.dist-info/entry_points.txt
xrcg-0.9.9.dist-info/licenses/LICENSE
xrcg-0.9.9.dist-info/WHEEL
xrcg-0.9.9.dist-info/METADATA
xrcg-0.9.9.dist-info/RECORD
