Metadata-Version: 2.4
Name: xrcg
Version: 0.9.9
Summary: A command-line tool for xRegistry with code generation for messaging and eventing applications
Author-email: Clemens Vasters <clemensv@microsoft.com>
Requires-Python: >=3.10
Classifier: Programming Language :: Python :: 3
Classifier: License :: OSI Approved :: MIT License
Classifier: Operating System :: OS Independent
License-File: LICENSE
Requires-Dist: jinja2>=3.1.4
Requires-Dist: jsonpointer>=3.0.0
Requires-Dist: pytest>=8.2.2
Requires-Dist: pandas>=2.2.2
Requires-Dist: pyyaml>=6.0.1
Requires-Dist: jsonschema>=4.22.0
Requires-Dist: pydot>=2.0.0
Requires-Dist: anytree>=2.12.1
Requires-Dist: avrotize>=2.22.2
Requires-Dist: avro>=1.11.3
Requires-Dist: toml>=0.10.2
Requires-Dist: platformdirs>=4.0.0
Requires-Dist: testcontainers>=4.8.2 ; extra == "dev"
Requires-Dist: pytest>=8.3.3 ; extra == "dev"
Provides-Extra: dev
